{
    "people": [
      {
        "name": "Dan",
        "age": 16
      },
      {
        "name": "Stan",
        "age": 102
      },
      {
        "name": "Danyl",
        "age": 55
      },
      {
        "name": "Grace",
        "age": 28
      },
      {
        "name": "Darren",
        "age": 23
      },
      {
        "name": "Collin",
        "age": 77
      },
      {
        "name": "Judy",
        "age": 27
      },
      {
        "name": "Drew",
        "age": 50
      },
      {
        "name": "Shawn",
        "age": 12
      },
      {
        "name": "Heather",
        "age": 40
      },
      {
        "name": "Sheila",
        "age": 8
      },
      {
        "name": "Donny",
        "age": 34
      },
      {
        "name": "Wendy",
        "age": 21
      },
      {
        "name": "Oscar",
        "age": 57
      },
      {
        "name": "April",
        "age": 36
      },
      {
        "name": "George",
        "age": 44
      },
      {
        "name": "Judith",
        "age": 90
      },
      {
        "name": "Abraham",
        "age": 90
      },
      {
        "name": "Emma",
        "age": 28
      },
      {
        "name": "Sophia",
        "age": 49
      },
      {
        "name": "Ava",
        "age": 55
      },
      {
        "name": "Isabella",
        "age": 25
      },
      {
        "name": "Olivia",
        "age": 57
      },
      {
        "name": "Kevin",
        "age": 9
      },
      {
        "name": "Leandro",
        "age": 66
      },
      {
        "name": "Hope",
        "age": 61
      },
      {
        "name": "Daniele",
        "age": 23
      },
      {
        "name": "Dane",
        "age": 25
      },
      {
        "name": "Gordon",
        "age": 34
      },
      {
        "name": "Angelo",
        "age": 22
      }
    ]
  }